{
  "document_id": "63edec83-8642-4b80-b8df-0324923e41cd",
  "title": "论文提炼｜FlowRAG: Continual Learning for Dynamic Retriever in Retrieval-Augmented Generation",
  "content": "论文名称：FlowRAG: Continual Learning for Dynamic Retriever in Retrieval-Augmented Generation\n研究主题：大模型推理、检索增强与记忆系统\n发表 venue：WWW - The Web Conference\n发表年份：2026\n作者：Senlei Zhang, Tongjun Shi, Dandan Song, Luan Zhang, Shuhao Zhang, Xiaofei Liao, Hai Jin\n作者角色：你是通讯作者\n一句话总结：Retrieval-Augmented Generation (RAG) enhances large language models by leveraging external knowledge, but retrieval quality degrades when corpora evolve continuously and distribution shift accumulates.\n核心内容：\nRetrieval-Augmented Generation (RAG) enhances large language models by leveraging external knowledge, but retrieval quality degrades when corpora evolve continuously and distribution shift accumulates. FlowRAG addresses this challenge by enabling lightweight continual retriever adaptation in evolving corpora. The framework augments the encoder with layer-wise prompt embeddings, introduces cross-layer fusion to capture hierarchical semantic representations, and employs a generator-guided loss to align retrieval decisions with generation likelihoods. Experiments across four domains show that by updating only about 0.64% of the model parameters, FlowRAG consistently improves retrieval accuracy, generation quality, and robustness to forgetting under non-stationary settings.\n适合回答的问题：\n- 这篇论文主要解决什么问题，以及它为什么重要。\n- 这篇论文的核心方法、系统设计或算法思路是什么。\n- 这篇论文与 大模型推理、检索增强与记忆系统 这条研究主线的关系是什么。",
  "tags": [
    "homepage",
    "research",
    "publication",
    "paper-digest",
    "rag",
    "continual-learning"
  ],
  "source_name": "homepage:contents/research_papers/publications_summary.md#0.3 FlowRAG: Continual Learning for Dynamic Retriever in Retrieval-Augmented Generation",
  "metadata": {
    "domain": "research",
    "identity": "pi",
    "material_type": "paper-digest",
    "source_kind": "homepage"
  },
  "created_at": "2026-05-28T01:19:22.839592Z"
}