{
  "document_id": "71051604-bcd2-4557-9ce9-c37dd5302080",
  "title": "课件正文｜研究生论文写作课程材料｜第 8 讲 研究生毕业论文中常见的问题（第1部分）",
  "content": "研究生论文写作课程 第八讲：研究生毕业论文中常见的问题 张书豪 华中科技大学 二〇二六年五月 欢迎在群里自由发言，课堂讨论与课后问题都可继续交流 扫码加入课程讨论群 群号：1092437119 张书豪 (华中科技大学) 研究生论文写作课程第八讲：研究生毕业论文中常见的问题 二〇二六年五月 1 / 39 课前热身 先判断一下 你见过的毕业论文问题，最常卡在哪一层？ 1 研究问题本身就没有站稳 2 章节很多，但前后不连 3 格式、图表、参考文献非常乱 4 三者都有，而且不知道先改什么 课程讨论群：2026 年研究生写作课 群号：1092437119 欢迎进群自由发言； 课堂上的临时想法、不同意见和课后追问都可以继续在群里交流。 张书豪 (华中科技大学) 研究生论文写作课程第八讲：研究生毕业论文中常见的问题 二〇二六年五月 2 / 39 课程定位：毕业论文修改首先是诊断问题层级 核心判断 毕业论文最常见的失败，不是某一句话写得不漂亮，而是把内容问题、结构问题和格式问 题混在一起处理，导致越改越乱。 本讲不再停留在抽象原则，而是直接讨论答辩前最常见、最伤说服力的问题。 重点不是“挑错”，而是建立一套有优先级的修订顺序。 能看出问题层级，才能决定哪里该重写，哪里只需整理。 张书豪 (华中科技大学) 研究生论文写作课程第八讲：研究生毕业论文中常见的问题 二〇二六年五月 3 / 39 学习目标 学会用“三层诊断法”区分毕业论文中的内容、结构和格式问题。 能识别引言、相关工作、方法、实验、结论各章节的典型失分点。 掌握答辩前更高效的修订顺序，避免把时间浪费在低优先级润色上。 形成一张可自查、可排序、可执行的论文体检单。 张书豪 (华中科技大学) 研究生论文写作课程第八讲：研究生毕业论文中常见的问题 二〇二六年五月 4 / 39 目录 1 三层诊断法：先判断问题出在哪一层 2 研究内容问题：根上站不住的典型表现 3 论文结构问题：章节之间为什么不说话 4 修订流程：答辩前如何高效体检与排序修改 张书豪 (华中科技大学) 研究生论文写作课程第八讲：研究生毕业论文中常见的问题 二〇二六年五月 5 / 39 01 三层诊断法 三层诊断法 第一层：研究内容是否成立 第二层：论文框架是否清楚 第三层：格式规范是否一致 张书豪 (华中科技大学) 研究生论文写作课程第八讲：研究生毕业论文中常见的问题 二〇二六年五月 7 / 39 为什么一定要按这个顺序改 错误顺序 正确顺序 先调格式、改语法、换图表配色，最后才发 先问研究内容是否成立，再问结构是否承载 现问题定义、章节逻辑和实验论点根本不成 得住，最后统一表达和格式。 立。 结论 内容问题不解决，结构调整没有意义； 结构不清，格式再漂亮也救不了答辩说服力。 张书豪 (华中科技大学) 研究生论文写作课程第八讲：研究生毕业论文中常见的问题 二〇二六年五月 8 / 39 先做一个快速体检：哪些症状最危险 表面症状 可能对应的问题层 风险 写了很多，但一句话 内容层 主问题不稳，整篇论文会失焦 说不清做什么 每章都完整，但彼此 结构层 答辩时很难建立整体贡献感 像独立报告 图表、引用、术语不 格式层 直接损伤论文专业感与可信度 统一 实验很多，却回答不 内容层 + 结构层 证据链断裂，最容易被追问 了核心论点 张书豪 (华中科技大学) 研究生论文写作课程第八讲：研究生毕业论文中常见的问题 二〇二六年五月 9 / 39 互动题：你会先从哪里改起？ 1 先把图表和参考文献整理整齐 2 先重写摘要和引言 3 先确认主问题、主贡献和关键证据是否对应 4 先改措辞，尽量让语言更高级 课程讨论群：2026 年研究生写作课 群号：1092437119 欢迎进群自由发言； 课堂上的临时想法、不同意见和课后追问都可以继续在群里交流。 张书豪 (华中科技大学) 研究生论文写作课程第八讲：研究生毕业论文中常见的问题 二〇二六年五月 10 / 39 02 研究内容问题 研究内容问题：根上站不住 问题定义不清：写了很多内容，但读者仍不知道到底解决什么问题。 贡献边界模糊：把已有工作、工程实现和真正创新混在一起。 实验与结论脱节：实验很多，但没有支撑核心论点。 研究动机不足：选题来源、价值和应用场景没有交代清楚。 内容堆砌：术语很多、章节很多，但主线不清。 张书豪 (华中科技大学) 研究生论文写作课程第八讲：研究生毕业论文中常见的问题 二〇二六年五月 12 / 39 内容层最常见的三个失配 问题与贡献失配 贡献与实验失配 章节与主线失配 问题讲得很大，贡献却只是 声称提升了效率、泛化或鲁 每章都在写东西，但不共同 局部工程实现。 棒性，但实验没有逐项对应。 服务一个核心问题。 张书豪 (华中科技大学) 研究生论文写作课程第八讲：研究生毕业论文中常见的问题 二〇二六年五月 13 / 39 一篇毕业论文至少要能回答四个内容问题 1 你到底解决了什么问题？ 2 这个问题为什么值得做，而不是只是“有意思”？ 3 你的核心贡献是什么，和已有工作差在哪？ 4 你的实验与分析是否真的在支撑这些贡献？ 判断标准 如果答辩前这四个问题还不能稳定回答，优先级最高的任务一定不是润色，而是回到内容 层重构。 张书豪 (华中科技大学) 研究生论文写作课程第八讲：研究生毕业论文中常见的问题 二〇二六年五月 14 / 39 案例诊断：这一段为什么危险 片段 随着人工智能技术的快速发展，相关应用越来越广泛，因此研究一个高效、准确、稳定的模型具有 重要意义。 本文针对该问题开展了系统研究，并设计了完整框架，实验结果表明方法具有良好效果。 没有说清“该问题”具体是什么。 高效、准确、稳定都是评价词，但没有任务边界和量化依据。 “系统研究”“完整框架”“良好效果”都在说好话，没有给信息。 张书豪 (华中科技大学) 研究生论文写作课程第八讲：研究生毕业论文中常见的问题 二〇二六年五月 15 / 39 课堂练习：从内容层挑出最需要重写的一句 练习要求 请回看自己的摘要或引言，圈出一句“听起来很对，但信息量很低”的句子，判断它是背景 空话、贡献空话，还是结果空话。 课程讨论群：2026 年研究生写作课 群号：1092437119 欢迎进群自由发言； 课堂上的临时想法、不同意见和课后追问都可以继续在群里交流。 张书豪 (华中科技大学) 研究生论文写作课程第八讲：研究生毕业论文中常见的问题 二〇二六年五月 16 / 39 内容层体检矩阵：先定位，再下手 维度 失分信号 优先动作 问题定义 写了很多背景，仍说不清要解决什么 用一句话写“对象 + 挑战 + 目标”， 放进引言首段 贡献描述 创新点像功能清单，缺少边界 把贡献改写为“相对谁、在何种条件 下、改进了什么” 证据链 实验结果多，但与主论点不对应 为每个贡献补上对应实验或分析条目 结论力度 结论过大、证据不足 收紧结论范围，主动写明适用边界 张书豪 (华中科技大学) 研究生论文写作课程第八讲：研究生毕业论文中常见的问题 二〇二六年五月 17 / 39 反例改写：把“空话段落”改成“可验证段落” 原句（问题） 本文提出一种高效且鲁棒的方法，在多个数据集上取得了良好效果。 改写（更可答辩） 针对长尾请求导致的推理延迟抖动问题，本文提出基于负载预测的动态调度策略； 在 X/Y/Z 三个 公开工作负载上，相比基线 A/B 将 P99 延迟分别降低 18%、23%、21%，并在高并发场景下保持吞 吐稳定。 从“评价词”改为“任务边界 + 比较对象 + 量化结果”。 把“好效果”拆成可复核、可追问的证据描述。",
  "tags": [
    "homepage",
    "teaching",
    "courseware",
    "pdf",
    "material:pdf",
    "identity:teacher",
    "domain:teaching",
    "audience:graduate",
    "course:paper-writing",
    "material:lecture",
    "lecture:8",
    "lecture"
  ],
  "source_name": "homepage:contents/teaching/graduate-paper-writing-course.md#公开课件::contents/teaching/graduate-paper-writing-course/2026/lecture-8-beamer.pdf::part-1",
  "metadata": {
    "material_type": "lecture",
    "identity": "teacher",
    "domain": "teaching",
    "audience": "graduate",
    "course_id": "paper-writing",
    "ordinal_type": "lecture",
    "ordinal": "8",
    "source_kind": "homepage"
  },
  "created_at": "2026-06-09T09:58:20.909857Z"
}