{
  "document_id": "9851c5d1-cff0-4d75-b076-1148e6f1cb76",
  "title": "Wiki | Intro",
  "content": "[Wiki: Intro](https://lab.sage.org.ai/sage-wiki/docs/intro)\n\n# Sage Wiki\n\n欢迎来到 **Sage Wiki** —— IntelliStream 团队知识库。\n\n这里存放团队的**技术成果、学习心得、教程指南**和**规范文档**，通过 Git 协作维护，人人皆可贡献。\n\n## 内容导航\n\n| 分类 | 说明 |\n|------|------|\n| [成果展示](/docs/achievements/) | 项目里程碑、技术产出、获奖记录 |\n| [学习教程](/docs/tutorials/) | 技术入门、工具使用、最佳实践 |\n| [技术心得](/docs/tech-notes/) | 踩坑记录、源码分析、架构设计 |\n| [团队规范](/docs/standards/) | 代码规范、工作流程、Review 准则 |\n| [资源汇总](/docs/resources/) | 推荐书单、工具清单、常用链接 |\n\n## 如何贡献\n\n1. Clone 本仓库\n2. 在对应分类目录下创建 Markdown 文件\n3. 提交 Pull Request 或直接 push 到 main 分支\n4. 站点自动构建部署\n\n:::tip 提示\n左侧边栏可以快速导航到各个分类下的文章。\n:::",
  "tags": [
    "wiki",
    "audience:public"
  ],
  "source_name": "wiki:intro",
  "metadata": {
    "audience": "public",
    "source_kind": "wiki",
    "wiki_url": "https://lab.sage.org.ai/sage-wiki/docs/intro",
    "wiki_category": "general"
  },
  "created_at": "2026-06-20T13:33:47.232976Z",
  "is_feedback_web": false,
  "review_status": "unknown",
  "freshness_status": "unknown",
  "reviewed_at": null,
  "reviewable": false
}